hydroforecast/__init__.py
hydroforecast/exp/__init__.py
hydroforecast/exp/base_exp.py
hydroforecast/exp/exp_path.py
hydroforecast/exp/hydrology_exp.py
hydroforecast/exp/keras_exp.py
hydroforecast/exp/paddle_exp.py
hydroforecast/exp/sklearn_exp.py
hydroforecast/exp/torch_exp.py
hydroforecast/loader/__init__.py
hydroforecast/loader/base_dataset.py
hydroforecast/loader/base_module.py
hydroforecast/models/MHA_LSTM.py
hydroforecast/models/__init__.py
hydroforecast/models/attention_models.py
hydroforecast/models/base_layers.py
hydroforecast/models/explain_rnn_models.py
hydroforecast/models/korea_transformer.py
hydroforecast/models/mlp_model.py
hydroforecast/models/torch_transformer.py
hydroforecast/models/transformer_model.py
hydroforecast/models/concept_models/__init__.py
hydroforecast/models/concept_models/gr4j.py
hydroforecast/models/concept_models/hymod.py
hydroforecast/models/concept_models/sac.py
hydroforecast/models/concept_models/xaj.py
hydroforecast/models/concept_models/flux/__init__.py
hydroforecast/models/concept_models/flux/abstraction.py
hydroforecast/models/concept_models/flux/area.py
hydroforecast/models/concept_models/flux/baseflow.py
hydroforecast/models/concept_models/flux/capillary.py
hydroforecast/models/concept_models/flux/depression.py
hydroforecast/models/concept_models/flux/effective.py
hydroforecast/models/concept_models/flux/evap.py
hydroforecast/models/concept_models/flux/excess.py
hydroforecast/models/concept_models/flux/exchange.py
hydroforecast/models/concept_models/flux/infiltration.py
hydroforecast/models/concept_models/flux/interception.py
hydroforecast/models/concept_models/flux/interflow.py
hydroforecast/models/concept_models/flux/melt.py
hydroforecast/models/concept_models/flux/percolation.py
hydroforecast/models/concept_models/flux/phenology.py
hydroforecast/models/concept_models/flux/rainfall.py
hydroforecast/models/concept_models/flux/recharge.py
hydroforecast/models/concept_models/flux/refreeze.py
hydroforecast-0.0.2.dist-info/METADATA
hydroforecast-0.0.2.dist-info/WHEEL
hydroforecast-0.0.2.dist-info/entry_points.txt
hydroforecast-0.0.2.dist-info/top_level.txt
hydroforecast-0.0.2.dist-info/RECORD
