Metadata-Version: 2.1
Name: hydroforecast
Version: 0.0.2
Summary: hydrology forecast (Concept model, ML model)
Home-page: https://github.com/chooron
Author: jingx
Author-email: jingxin0107@qq.com
Maintainer: jingx
Maintainer-email: jingxin0107@qq.com
License: MIT License
Platform: UNKNOWN
Classifier: Development Status :: 3 - Alpha
Classifier: Intended Audience :: Developers
Classifier: Topic :: Software Development :: Build Tools
Classifier: License :: OSI Approved :: MIT License
Classifier: Programming Language :: Python :: 3.7
Requires-Python: >=3.7
